genanki_chinese-0.1.6.data/scripts/genanki-chinese
genankichinese/__init__.py
genankichinese/exporter.py
genankichinese/generator.py
genankichinese/importer.py
genankichinese/main.py
genankichinese/updater.py
genanki_chinese-0.1.6.dist-info/LICENSE
genanki_chinese-0.1.6.dist-info/METADATA
genanki_chinese-0.1.6.dist-info/WHEEL
genanki_chinese-0.1.6.dist-info/top_level.txt
genanki_chinese-0.1.6.dist-info/RECORD
