Metadata-Version: 2.1
Name: genanki-chinese
Version: 0.1.6
Summary: Packages which automates the creation and update of chinese notes for Anki
Home-page: https://github.com/RubenSerradas/genanki-chinese
Author: Ruben Serradas
Author-email: rubenserradas@gmail.com
License: UNKNOWN
Project-URL: Bug Tracker, https://github.com/RubenSerradas/genanki-chinese/issues
Platform: UNKNOWN
Classifier: Programming Language :: Python :: 3
Classifier: License :: OSI Approved :: GNU General Public License v3 (GPLv3)
Classifier: Operating System :: OS Independent
Classifier: Intended Audience :: Education
Requires-Python: >=3.8
License-File: LICENSE
Requires-Dist: genanki
Requires-Dist: requests
Requires-Dist: OpenCC
Requires-Dist: pypinyin
Requires-Dist: gTTS
Requires-Dist: googletrans (==4.0.0rc1)
